{
  "$schema": "https://raw.githubusercontent.com/googleapis/release-please/main/schemas/config.json",
  "include-component-in-tag": false,
  "packages": {
    ".": {
      "release-type": "simple",
      "changelog-sections": [
        { "type": "feat", "section": "Features" },
        { "type": "fix", "section": "Bug Fixes" },
        { "type": "perf", "section": "Performance Improvements" },
        { "type": "refactor", "section": "Code Refactoring" },
        { "type": "ci", "section": "Continuous Integration" },
        { "type": "build", "section": "Build System" },
        { "type": "docs", "section": "Documentation", "hidden": true },
        { "type": "test", "section": "Tests", "hidden": true },
        { "type": "chore", "section": "Miscellaneous", "hidden": true }
      ]
    }
  }
}
